text2num-3.0.0.dist-info/METADATA
text2num-3.0.0.dist-info/WHEEL
text2num-3.0.0.dist-info/licenses/LICENSE
text_to_num/__init__.py
text_to_num/_text2num.cpython-310-i386-linux-gnu.so
text2num-3.0.0.dist-info/RECORD
