Metadata-Version: 2.4
Name: text2num
Version: 3.0.0
Classifier: Programming Language :: Rust
Classifier: Programming Language :: Python :: Implementation :: CPython
Classifier: Programming Language :: Python :: Implementation :: PyPy
Classifier: Development Status :: 5 - Production/Stable
Classifier: License :: OSI Approved :: MIT License
Classifier: Topic :: Text Processing :: Linguistic
Classifier: Topic :: Text Processing :: Filters
Classifier: Natural Language :: French
Classifier: Natural Language :: English
Classifier: Natural Language :: Spanish
Classifier: Natural Language :: Portuguese
Classifier: Natural Language :: German
Classifier: Natural Language :: Dutch
Classifier: Natural Language :: Italian
License-File: LICENSE
Summary: Parse and convert numbers written in French, Spanish, English, Portuguese, German, Dutch or Italian into their digit representation.
Keywords: French,Spanish,English,Portuguese,German,Italian,Dutch,NLP,words-to-numbers
Author-email: Allo-Media <contact@allo-media.fr>
License: MIT
Requires-Python: >=3.8
Project-URL: Homepage, https://github.com/allo-media/text2num
Project-URL: Documentation, https://text2num.readthedocs.io
Project-URL: Repository, https://github.com/allo-media/text2num
Project-URL: Issues, https://github.com/allo-media/text2num/issues
Project-URL: Changelog, https://github.com/allo-media/text2num/releases
